Metadata-Version: 2.4
Name: automagik-tools
Version: 0.9.8
Summary: A monorepo package for MCP tools with dynamic loading capabilities - featuring Evolution API v2 WhatsApp integration
Author-email: Felipe Rosa <felipe@namastex.ai>, Cezar Vasconcelos <cezar@namastex.ai>
License: MIT
Project-URL: Homepage, https://github.com/namastexlabs/automagik-tools
Project-URL: Documentation, https://github.com/namastexlabs/automagik-tools/README.md
Project-URL: Repository, https://github.com/namastexlabs/automagik-tools
Project-URL: Issues, https://github.com/namastexlabs/automagik-tools/issues
Keywords: mcp,tools,ai,agents,fastmcp,whatsapp,discord,notion
Classifier: Development Status :: 3 - Alpha
Classifier: Intended Audience :: Developers
Classifier: License :: OSI Approved :: MIT License
Classifier: Programming Language :: Python :: 3
Classifier: Programming Language :: Python :: 3.10
Classifier: Programming Language :: Python :: 3.11
Classifier: Programming Language :: Python :: 3.12
Classifier: Topic :: Software Development :: Libraries :: Python Modules
Classifier: Topic :: Communications :: Chat
Classifier: Topic :: Office/Business
Requires-Python: >=3.10
License-File: LICENSE
Requires-Dist: fastmcp>=2.10.0
Requires-Dist: fastapi>=0.104.0
Requires-Dist: uvicorn>=0.24.0
Requires-Dist: pydantic>=2.10.0
Requires-Dist: pydantic-settings>=2.5.0
Requires-Dist: typer>=0.15.0
Requires-Dist: rich>=13.0.0
Requires-Dist: importlib-metadata>=6.0.0
Requires-Dist: watchdog>=3.0.0
Requires-Dist: pyyaml>=6.0.1
Requires-Dist: build>=1.2.2.post1
Requires-Dist: twine>=6.1.0
Requires-Dist: psutil>=7.0.0
Requires-Dist: agno>=1.5.9
Requires-Dist: openai>=1.84.0
Requires-Dist: sqlalchemy>=2.0.41
Requires-Dist: google-genai>=0.5.0
Requires-Dist: python-dotenv>=1.1.0
Requires-Dist: httpx>=0.28.1
Provides-Extra: evolution-api
Requires-Dist: httpx>=0.28.1; extra == "evolution-api"
Requires-Dist: python-dotenv>=1.1.0; extra == "evolution-api"
Provides-Extra: automagik
Requires-Dist: httpx>=0.28.1; extra == "automagik"
Requires-Dist: python-dotenv>=1.1.0; extra == "automagik"
Requires-Dist: agno>=0.1.0; extra == "automagik"
Requires-Dist: openai>=1.0.0; extra == "automagik"
Provides-Extra: automagik-enhanced
Requires-Dist: httpx>=0.28.1; extra == "automagik-enhanced"
Requires-Dist: python-dotenv>=1.1.0; extra == "automagik-enhanced"
Requires-Dist: agno>=0.1.0; extra == "automagik-enhanced"
Requires-Dist: openai>=1.0.0; extra == "automagik-enhanced"
Requires-Dist: markdown>=3.0.0; extra == "automagik-enhanced"
Provides-Extra: ask
Requires-Dist: httpx>=0.28.1; extra == "ask"
Requires-Dist: python-dotenv>=1.1.0; extra == "ask"
Requires-Dist: openai>=1.84.0; extra == "ask"
Provides-Extra: genie
Requires-Dist: agno>=1.5.9; extra == "genie"
Requires-Dist: openai>=1.84.0; extra == "genie"
Requires-Dist: sqlalchemy>=2.0.41; extra == "genie"
Requires-Dist: python-dotenv>=1.1.0; extra == "genie"
Provides-Extra: gemini-assistant
Requires-Dist: google-genai>=0.5.0; extra == "gemini-assistant"
Requires-Dist: python-dotenv>=1.1.0; extra == "gemini-assistant"
Provides-Extra: automagik-hive
Requires-Dist: httpx>=0.28.1; extra == "automagik-hive"
Requires-Dist: python-dotenv>=1.1.0; extra == "automagik-hive"
Provides-Extra: discord
Requires-Dist: discord.py>=2.3.0; extra == "discord"
Requires-Dist: python-dotenv>=1.1.0; extra == "discord"
Provides-Extra: notion
Requires-Dist: notion-client>=2.0.0; extra == "notion"
Requires-Dist: python-dotenv>=1.1.0; extra == "notion"
Provides-Extra: github
Requires-Dist: pygithub>=2.1.0; extra == "github"
Requires-Dist: python-dotenv>=1.1.0; extra == "github"
Provides-Extra: dev
Requires-Dist: pytest>=7.0.0; extra == "dev"
Requires-Dist: pytest-asyncio>=0.21.0; extra == "dev"
Requires-Dist: pytest-cov>=4.0.0; extra == "dev"
Requires-Dist: pytest-timeout>=2.1.0; extra == "dev"
Requires-Dist: black>=23.0.0; extra == "dev"
Requires-Dist: ruff>=0.1.0; extra == "dev"
Requires-Dist: mypy>=1.0.0; extra == "dev"
Requires-Dist: pre-commit>=3.0.0; extra == "dev"
Provides-Extra: all
Requires-Dist: automagik-tools[ask,automagik,automagik-enhanced,automagik-hive,discord,evolution-api,github,notion]; extra == "all"
Dynamic: license-file
